<?xml version="1.0" encoding="utf-8" ?><workflow xmlns="http://vmware.com/vco/workflow" xmlns:xsi="http://www.w3.org/2001/XMLSchema-instance" xsi:schemaLocation="http://vmware.com/vco/workflow http://vmware.com/vco/workflow/Workflow-v4.xsd" root-name="item1" object-name="workflow:name=generic" id="193a306a-a95c-3569-a8ec-b3b60455f326" version="1.0.0" api-version="6.0.0" restartMode="1" resumeFromFailedMode="0"><display-name><![CDATA[Waitin Timer Edge 2]]></display-name><description><![CDATA[Waiting timer will point to shouldGoHere with target]]></description><position x="105" y="45.90909090909091" /><attrib name="waitingTimer" type="Date" read-only="false" /><attrib name="counter" type="number" read-only="false" /><workflow-item name="item0" type="end" end-mode="0"><position x="585.0" y="45.40909090909091" /></workflow-item><workflow-item name="item1" out-name="item2" type="waiting-timer"><display-name><![CDATA[waitForEvent]]></display-name><in-binding><bind name="timer.date" type="Date" export-name="waitingTimer" /></in-binding><position x="225.0" y="55.40909090909091" /></workflow-item><workflow-item name="item2" out-name="item0" type="task"><script encoded="false"><![CDATA[]]></script><display-name><![CDATA[shouldGoHere]]></display-name><position x="385.0" y="55.40909090909091" /></workflow-item><presentation><p-param name="waitingTimer"><desc><![CDATA[waitingTimer]]></desc></p-param></presentation></workflow>